textalloc/__init__.py
textalloc/candidates.py
textalloc/non_overlapping_boxes.py
textalloc/overlap_functions.py
textalloc/py.typed
textalloc-1.2.1.dist-info/licenses/LICENSE
textalloc-1.2.1.dist-info/METADATA
textalloc-1.2.1.dist-info/WHEEL
textalloc-1.2.1.dist-info/top_level.txt
textalloc-1.2.1.dist-info/RECORD
