Metadata-Version: 2.4
Name: textalloc
Version: 1.2.1
Summary: Efficient Text Allocation in matplotlib using NumPy Broadcasting
Author-email: Christoffer Kjellson <c.kjellson@gmail.com>
License: MIT License
Project-URL: Homepage, https://github.com/ckjellson/textalloc
Project-URL: Bug Tracker, https://github.com/ckjellson/textalloc/issues
Classifier: Programming Language :: Python :: 3
Classifier: License :: OSI Approved :: MIT License
Classifier: Operating System :: OS Independent
Requires-Python: >=3.6
License-File: LICENSE
Requires-Dist: tqdm; python_version > "3.6"
Requires-Dist: numpy
Requires-Dist: matplotlib
Requires-Dist: packaging
Dynamic: license-file
